chunkator/__init__.py
django_chunkator-2.0.0.dist-info/METADATA
django_chunkator-2.0.0.dist-info/RECORD
django_chunkator-2.0.0.dist-info/WHEEL
django_chunkator-2.0.0.dist-info/namespace_packages.txt
django_chunkator-2.0.0.dist-info/top_level.txt
