Metadata-Version: 2.1
Name: django-chunkator
Version: 2.0.0
Summary: Chunk large QuerySets into small chunks, and iterate over them without killing your RAM.
Home-page: https://github.com/peopledoc/django-chunkator
Author: PeopleDoc
Author-email: rd@people-doc.com
License: MIT
Platform: UNKNOWN
Classifier: Environment :: Web Environment
Classifier: Framework :: Django
Classifier: Operating System :: OS Independent
Classifier: Programming Language :: Python
Classifier: Programming Language :: Python :: 3
Classifier: Programming Language :: Python :: 3.5
Classifier: Programming Language :: Python :: 3.6
Classifier: Programming Language :: Python :: 3.7
Classifier: Programming Language :: Python :: 3.8
Classifier: Topic :: Internet :: WWW/HTTP
Classifier: Topic :: Internet :: WWW/HTTP :: Dynamic Content
Classifier: License :: OSI Approved :: MIT License
Requires-Dist: django
